smolcrawl/__init__.py
smolcrawl/crawl.py
smolcrawl/db.py
smolcrawl/utils.py
smolcrawl-0.1.7.dist-info/licenses/LICENSE.md
smolcrawl-0.1.7.dist-info/METADATA
smolcrawl-0.1.7.dist-info/WHEEL
smolcrawl-0.1.7.dist-info/entry_points.txt
smolcrawl-0.1.7.dist-info/top_level.txt
smolcrawl-0.1.7.dist-info/RECORD
