Metadata-Version: 2.4
Name: smolcrawl
Version: 0.1.7
Summary: Crawls and indexes websites for local LLM work
Author-email: Bill Chambers <contact@learnbybuilding.ai>
License-Expression: MIT
Project-URL: Homepage, https://github.com/bllchmbrs/smolcrawl
Classifier: Programming Language :: Python :: 3
Classifier: Operating System :: OS Independent
Requires-Python: >=3.11
License-File: LICENSE.md
Requires-Dist: crawlee[all]>=0.6.7
Requires-Dist: diskcache>=5.6.3
Requires-Dist: loguru>=0.7.3
Requires-Dist: markdownify>=1.1.0
Requires-Dist: python-dotenv>=1.1.0
Requires-Dist: readabilipy>=0.3.0
Requires-Dist: tantivy>=0.22.2
Requires-Dist: typer>=0.15.2
Dynamic: license-file
